{
 "source": "espn",
 "event": "Uruguay at Ghana",
 "date": "2022-12-02T15:00Z",
 "teams": {
  "Ghana": {
   "fouls": 18,
   "yellows": 2,
   "reds": 0,
   "offsides": 2,
   "corners": 5,
   "sot": 4
  },
  "Uruguay": {
   "fouls": 11,
   "yellows": 5,
   "reds": 0,
   "offsides": 2,
   "corners": 2,
   "sot": 7
  }
 },
 "players": [
  {
   "team": "Ghana",
   "name": "Lawrence Ati Zigi",
   "position": "G",
   "starter": true,
   "minutes": 90,
   "totalShots": 0,
   "shotsOnTarget": 0,
   "totalGoals": 0,
   "goalAssists": 0,
   "foulsCommitted": 0,
   "offsides": 0,
   "yellowCards": 0,
   "redCards": 0
  },
  {
   "team": "Ghana",
   "name": "Mohammed Salisu",
   "position": "CD-L",
   "starter": true,
   "minutes": 90,
   "totalShots": 0,
   "shotsOnTarget": 0,
   "totalGoals": 0,
   "goalAssists": 0,
   "foulsCommitted": 2,
   "offsides": 0,
   "yellowCards": 0,
   "redCards": 0
  },
  {
   "team": "Ghana",
   "name": "Daniel Amartey",
   "position": "CD-R",
   "starter": true,
   "minutes": 90,
   "totalShots": 1,
   "shotsOnTarget": 0,
   "totalGoals": 0,
   "goalAssists": 0,
   "foulsCommitted": 0,
   "offsides": 0,
   "yellowCards": 0,
   "redCards": 0
  },
  {
   "team": "Ghana",
   "name": "Baba Rahman",
   "position": "LB",
   "starter": true,
   "minutes": 90,
   "totalShots": 0,
   "shotsOnTarget": 0,
   "totalGoals": 0,
   "goalAssists": 0,
   "foulsCommitted": 4,
   "offsides": 0,
   "yellowCards": 0,
   "redCards": 0
  },
  {
   "team": "Ghana",
   "name": "Alidu Seidu",
   "position": "RB",
   "starter": true,
   "minutes": 90,
   "totalShots": 0,
   "shotsOnTarget": 0,
   "totalGoals": 0,
   "goalAssists": 0,
   "foulsCommitted": 2,
   "offsides": 0,
   "yellowCards": 1,
   "redCards": 0
  },
  {
   "team": "Ghana",
   "name": "Andr\u00e9 Ayew",
   "position": "AM",
   "starter": true,
   "minutes": 65,
   "totalShots": 0,
   "shotsOnTarget": 0,
   "totalGoals": 0,
   "goalAssists": 0,
   "foulsCommitted": 0,
   "offsides": 0,
   "yellowCards": 0,
   "redCards": 0
  },
  {
   "team": "Ghana",
   "name": "Salis Abdul Samed",
   "position": "LM",
   "starter": true,
   "minutes": 65,
   "totalShots": 0,
   "shotsOnTarget": 0,
   "totalGoals": 0,
   "goalAssists": 0,
   "foulsCommitted": 2,
   "offsides": 0,
   "yellowCards": 0,
   "redCards": 0
  },
  {
   "team": "Ghana",
   "name": "Thomas Partey",
   "position": "RM",
   "starter": true,
   "minutes": 90,
   "totalShots": 0,
   "shotsOnTarget": 0,
   "totalGoals": 0,
   "goalAssists": 0,
   "foulsCommitted": 2,
   "offsides": 0,
   "yellowCards": 0,
   "redCards": 0
  },
  {
   "team": "Ghana",
   "name": "Mohammed Kudus",
   "position": "F",
   "starter": true,
   "minutes": 65,
   "totalShots": 4,
   "shotsOnTarget": 0,
   "totalGoals": 0,
   "goalAssists": 0,
   "foulsCommitted": 2,
   "offsides": 1,
   "yellowCards": 0,
   "redCards": 0
  },
  {
   "team": "Ghana",
   "name": "Jordan Ayew",
   "position": "AM-L",
   "starter": true,
   "minutes": 65,
   "totalShots": 1,
   "shotsOnTarget": 1,
   "totalGoals": 0,
   "goalAssists": 0,
   "foulsCommitted": 1,
   "offsides": 0,
   "yellowCards": 0,
   "redCards": 0
  },
  {
   "team": "Ghana",
   "name": "I\u00f1aki Williams",
   "position": "AM-R",
   "starter": true,
   "minutes": 65,
   "totalShots": 0,
   "shotsOnTarget": 0,
   "totalGoals": 0,
   "goalAssists": 0,
   "foulsCommitted": 0,
   "offsides": 0,
   "yellowCards": 0,
   "redCards": 0
  },
  {
   "team": "Ghana",
   "name": "Daniel-Kofi Kyereh",
   "position": "SUB",
   "starter": false,
   "minutes": 25,
   "totalShots": 0,
   "shotsOnTarget": 0,
   "totalGoals": 0,
   "goalAssists": 0,
   "foulsCommitted": 0,
   "offsides": 0,
   "yellowCards": 0,
   "redCards": 0
  },
  {
   "team": "Ghana",
   "name": "Kamaldeen Sulemana",
   "position": "SUB",
   "starter": false,
   "minutes": 25,
   "totalShots": 1,
   "shotsOnTarget": 1,
   "totalGoals": 0,
   "goalAssists": 0,
   "foulsCommitted": 1,
   "offsides": 0,
   "yellowCards": 1,
   "redCards": 0
  },
  {
   "team": "Ghana",
   "name": "Fatawu Issahaku",
   "position": "SUB",
   "starter": false,
   "minutes": 25,
   "totalShots": 0,
   "shotsOnTarget": 0,
   "totalGoals": 0,
   "goalAssists": 0,
   "foulsCommitted": 0,
   "offsides": 0,
   "yellowCards": 0,
   "redCards": 0
  },
  {
   "team": "Ghana",
   "name": "Osman Bukari",
   "position": "SUB",
   "starter": false,
   "minutes": 25,
   "totalShots": 1,
   "shotsOnTarget": 0,
   "totalGoals": 0,
   "goalAssists": 0,
   "foulsCommitted": 0,
   "offsides": 1,
   "yellowCards": 0,
   "redCards": 0
  },
  {
   "team": "Ghana",
   "name": "Antoine Semenyo",
   "position": "SUB",
   "starter": false,
   "minutes": 25,
   "totalShots": 1,
   "shotsOnTarget": 0,
   "totalGoals": 0,
   "goalAssists": 0,
   "foulsCommitted": 0,
   "offsides": 0,
   "yellowCards": 0,
   "redCards": 0
  },
  {
   "team": "Uruguay",
   "name": "Sergio Rochet",
   "position": "G",
   "starter": true,
   "minutes": 90,
   "totalShots": 0,
   "shotsOnTarget": 0,
   "totalGoals": 0,
   "goalAssists": 0,
   "foulsCommitted": 1,
   "offsides": 0,
   "yellowCards": 0,
   "redCards": 0
  },
  {
   "team": "Uruguay",
   "name": "Sebasti\u00e1n Coates",
   "position": "CD-L",
   "starter": true,
   "minutes": 90,
   "totalShots": 1,
   "shotsOnTarget": 0,
   "totalGoals": 0,
   "goalAssists": 0,
   "foulsCommitted": 1,
   "offsides": 0,
   "yellowCards": 1,
   "redCards": 0
  },
  {
   "team": "Uruguay",
   "name": "Jos\u00e9 Mar\u00eda Gim\u00e9nez",
   "position": "CD-R",
   "starter": true,
   "minutes": 90,
   "totalShots": 1,
   "shotsOnTarget": 0,
   "totalGoals": 0,
   "goalAssists": 0,
   "foulsCommitted": 0,
   "offsides": 0,
   "yellowCards": 1,
   "redCards": 0
  },
  {
   "team": "Uruguay",
   "name": "Math\u00edas Olivera",
   "position": "LB",
   "starter": true,
   "minutes": 90,
   "totalShots": 0,
   "shotsOnTarget": 0,
   "totalGoals": 0,
   "goalAssists": 0,
   "foulsCommitted": 1,
   "offsides": 0,
   "yellowCards": 0,
   "redCards": 0
  },
  {
   "team": "Uruguay",
   "name": "Guillermo Varela",
   "position": "RB",
   "starter": true,
   "minutes": 90,
   "totalShots": 0,
   "shotsOnTarget": 0,
   "totalGoals": 0,
   "goalAssists": 0,
   "foulsCommitted": 2,
   "offsides": 0,
   "yellowCards": 0,
   "redCards": 0
  },
  {
   "team": "Uruguay",
   "name": "Rodrigo Bentancur",
   "position": "CM-L",
   "starter": true,
   "minutes": 65,
   "totalShots": 0,
   "shotsOnTarget": 0,
   "totalGoals": 0,
   "goalAssists": 0,
   "foulsCommitted": 3,
   "offsides": 0,
   "yellowCards": 0,
   "redCards": 0
  },
  {
   "team": "Uruguay",
   "name": "Federico Valverde",
   "position": "CM-R",
   "starter": true,
   "minutes": 90,
   "totalShots": 2,
   "shotsOnTarget": 0,
   "totalGoals": 0,
   "goalAssists": 0,
   "foulsCommitted": 3,
   "offsides": 0,
   "yellowCards": 0,
   "redCards": 0
  },
  {
   "team": "Uruguay",
   "name": "Giorgian de Arrascaeta",
   "position": "LM",
   "starter": true,
   "minutes": 65,
   "totalShots": 2,
   "shotsOnTarget": 2,
   "totalGoals": 2,
   "goalAssists": 0,
   "foulsCommitted": 0,
   "offsides": 0,
   "yellowCards": 0,
   "redCards": 0
  },
  {
   "team": "Uruguay",
   "name": "Facundo Pellistri",
   "position": "RM",
   "starter": true,
   "minutes": 65,
   "totalShots": 1,
   "shotsOnTarget": 0,
   "totalGoals": 0,
   "goalAssists": 0,
   "foulsCommitted": 0,
   "offsides": 0,
   "yellowCards": 0,
   "redCards": 0
  },
  {
   "team": "Uruguay",
   "name": "Darwin N\u00fa\u00f1ez",
   "position": "CF-L",
   "starter": true,
   "minutes": 65,
   "totalShots": 1,
   "shotsOnTarget": 0,
   "totalGoals": 0,
   "goalAssists": 0,
   "foulsCommitted": 0,
   "offsides": 0,
   "yellowCards": 1,
   "redCards": 0
  },
  {
   "team": "Uruguay",
   "name": "Luis Su\u00e1rez",
   "position": "CF-R",
   "starter": true,
   "minutes": 65,
   "totalShots": 2,
   "shotsOnTarget": 1,
   "totalGoals": 0,
   "goalAssists": 1,
   "foulsCommitted": 0,
   "offsides": 0,
   "yellowCards": 1,
   "redCards": 0
  },
  {
   "team": "Uruguay",
   "name": "Edinson Cavani",
   "position": "SUB",
   "starter": false,
   "minutes": 25,
   "totalShots": 0,
   "shotsOnTarget": 0,
   "totalGoals": 0,
   "goalAssists": 0,
   "foulsCommitted": 0,
   "offsides": 0,
   "yellowCards": 1,
   "redCards": 0
  },
  {
   "team": "Uruguay",
   "name": "Agust\u00edn Canobbio",
   "position": "SUB",
   "starter": false,
   "minutes": 25,
   "totalShots": 0,
   "shotsOnTarget": 0,
   "totalGoals": 0,
   "goalAssists": 0,
   "foulsCommitted": 0,
   "offsides": 0,
   "yellowCards": 0,
   "redCards": 0
  },
  {
   "team": "Uruguay",
   "name": "Mat\u00edas Vecino",
   "position": "SUB",
   "starter": false,
   "minutes": 25,
   "totalShots": 0,
   "shotsOnTarget": 0,
   "totalGoals": 0,
   "goalAssists": 0,
   "foulsCommitted": 0,
   "offsides": 0,
   "yellowCards": 0,
   "redCards": 0
  },
  {
   "team": "Uruguay",
   "name": "Nicol\u00e1s de la Cruz",
   "position": "SUB",
   "starter": false,
   "minutes": 25,
   "totalShots": 1,
   "shotsOnTarget": 0,
   "totalGoals": 0,
   "goalAssists": 0,
   "foulsCommitted": 0,
   "offsides": 1,
   "yellowCards": 0,
   "redCards": 0
  },
  {
   "team": "Uruguay",
   "name": "Maxi G\u00f3mez",
   "position": "SUB",
   "starter": false,
   "minutes": 25,
   "totalShots": 1,
   "shotsOnTarget": 1,
   "totalGoals": 0,
   "goalAssists": 0,
   "foulsCommitted": 0,
   "offsides": 0,
   "yellowCards": 0,
   "redCards": 0
  }
 ],
 "referee": "Daniel Siebert"
}